overfit/__init__.py
overfit-0.0.1.dist-info/LICENSE
overfit-0.0.1.dist-info/METADATA
overfit-0.0.1.dist-info/WHEEL
overfit-0.0.1.dist-info/top_level.txt
overfit-0.0.1.dist-info/RECORD
