Metadata-Version: 2.1
Name: overfit
Version: 0.0.1
Summary: An ML code generator
Author: hech
Author-email: 
Project-URL: Homepage, https://github.com/hech/overfit
Project-URL: Issues, https://github.com/hech/overfit/issues
Classifier: Programming Language :: Python :: 3
Classifier: License :: OSI Approved :: MIT License
Classifier: Operating System :: OS Independent
Requires-Python: >=3.8
License-File: LICENSE
